openmcp/__init__.py
openmcp/cli.py
openmcp/client.py
openmcp/api/__init__.py
openmcp/api/mcp_server.py
openmcp/api/models.py
openmcp/api/routes.py
openmcp/core/__init__.py
openmcp/core/auth.py
openmcp/core/config.py
openmcp/core/mcp_registry.py
openmcp/core/server.py
openmcp/services/__init__.py
openmcp/services/base.py
openmcp/services/browseruse_service.py
openmcp/services/web_crawler_service.py
openmcp/services/web_search_service.py
openmcp/utils/__init__.py
openmcp/utils/logging.py
openmcp-0.6.0.dist-info/licenses/LICENSE
openmcp-0.6.0.dist-info/METADATA
openmcp-0.6.0.dist-info/WHEEL
openmcp-0.6.0.dist-info/entry_points.txt
openmcp-0.6.0.dist-info/top_level.txt
openmcp-0.6.0.dist-info/RECORD
