Metadata-Version: 2.4
Name: openmcp
Version: 0.6.0
Summary: A collection of optimized MCP services for AI Agents
Author: openmcp contributors
License: MIT
Project-URL: Homepage, https://openmcp.pro
Project-URL: Repository, https://github.com/openmcp-pro/openmcp
Project-URL: Documentation, https://openmcp.pro/docs
Project-URL: Issues, https://github.com/openmcp-pro/openmcp/issues
Keywords: mcp,ai,agents,browser,automation
Classifier: Development Status :: 4 - Beta
Classifier: Intended Audience :: Developers
Classifier: License :: OSI Approved :: MIT License
Classifier: Programming Language :: Python :: 3
Classifier: Programming Language :: Python :: 3.9
Classifier: Programming Language :: Python :: 3.10
Classifier: Programming Language :: Python :: 3.11
Classifier: Programming Language :: Python :: 3.12
Classifier: Topic :: Software Development :: Libraries :: Python Modules
Classifier: Topic :: Internet :: WWW/HTTP :: Browsers
Requires-Python: >=3.9
License-File: LICENSE
Requires-Dist: fastapi>=0.104.0
Requires-Dist: uvicorn[standard]>=0.24.0
Requires-Dist: pydantic>=2.5.0
Requires-Dist: httpx>=0.25.0
Requires-Dist: python-multipart>=0.0.6
Requires-Dist: python-jose[cryptography]>=3.3.0
Requires-Dist: passlib[bcrypt]>=1.7.4
Requires-Dist: selenium>=4.15.0
Requires-Dist: webdriver-manager>=4.0.0
Requires-Dist: aiofiles>=23.2.0
Requires-Dist: structlog>=23.2.0
Requires-Dist: rich>=13.7.0
Requires-Dist: typer>=0.9.0
Requires-Dist: pyyaml>=6.0.1
Requires-Dist: mcp>=1.0.0
Provides-Extra: dev
Requires-Dist: pytest>=7.4.0; extra == "dev"
Requires-Dist: pytest-asyncio>=0.21.0; extra == "dev"
Requires-Dist: black>=23.9.0; extra == "dev"
Requires-Dist: isort>=5.12.0; extra == "dev"
Requires-Dist: flake8>=6.1.0; extra == "dev"
Requires-Dist: mypy>=1.6.0; extra == "dev"
Requires-Dist: pre-commit>=3.5.0; extra == "dev"
Dynamic: license-file
